shared_storage_client/__init__.py
shared_storage_client/storage_client.py
shared_storage_client_5-0.1.0.dist-info/METADATA
shared_storage_client_5-0.1.0.dist-info/WHEEL
shared_storage_client_5-0.1.0.dist-info/top_level.txt
shared_storage_client_5-0.1.0.dist-info/RECORD
