Metadata-Version: 2.1
Name: shared_storage_client_5
Version: 0.1.0
Summary: Storage Client For Microservices
Author: Chris Maresca
Author-email: chris@workmait.ai
Classifier: Programming Language :: Python :: 3
Classifier: License :: OSI Approved :: MIT License
Classifier: Operating System :: OS Independent
Requires-Python: >=3.8
Requires-Dist: boto3
Requires-Dist: s3fs
Requires-Dist: python-dotenv
